Flushed/RecentUseCache.py
Flushed/__init__.py
Flushed-1.0.0.dist-info/METADATA
Flushed-1.0.0.dist-info/WHEEL
Flushed-1.0.0.dist-info/top_level.txt
Flushed-1.0.0.dist-info/RECORD
