Metadata-Version: 2.1
Name: Flushed
Version: 1.0.0
Summary: Library to work with in memory buffers and caches
Home-page: UNKNOWN
Author: Alan Bacon
Author-email: alan@bacontowers.co.uk
License: UNKNOWN
Platform: UNKNOWN
